trphysx/__init__.py
trphysx/config/__init__.py
trphysx/config/arg_parser.py
trphysx/config/args.py
trphysx/config/configuration_auto.py
trphysx/config/configuration_cylinder.py
trphysx/config/configuration_grayscott.py
trphysx/config/configuration_lorenz.py
trphysx/config/configuration_phys.py
trphysx/data_utils/__init__.py
trphysx/data_utils/data_utils.py
trphysx/data_utils/dataset_auto.py
trphysx/data_utils/dataset_cylinder.py
trphysx/data_utils/dataset_grayscott.py
trphysx/data_utils/dataset_lorenz.py
trphysx/data_utils/dataset_phys.py
trphysx/embedding/__init__.py
trphysx/embedding/embedding_auto.py
trphysx/embedding/embedding_cylinder.py
trphysx/embedding/embedding_grayscott.py
trphysx/embedding/embedding_lorenz.py
trphysx/embedding/embedding_model.py
trphysx/embedding/training/__init__.py
trphysx/embedding/training/enn_args.py
trphysx/embedding/training/enn_data_handler.py
trphysx/embedding/training/enn_trainer.py
trphysx/transformer/__init__.py
trphysx/transformer/attention.py
trphysx/transformer/generate_utils.py
trphysx/transformer/phys_transformer_base.py
trphysx/transformer/phys_transformer_gpt2.py
trphysx/transformer/phys_transformer_helpers.py
trphysx/transformer/utils.py
trphysx/utils/__init__.py
trphysx/utils/metrics.py
trphysx/utils/trainer.py
trphysx/viz/__init__.py
trphysx/viz/viz_auto.py
trphysx/viz/viz_cylinder.py
trphysx/viz/viz_grayscott.py
trphysx/viz/viz_lorenz.py
trphysx/viz/viz_model.py
trphysx-0.0.8.dist-info/LICENSE
trphysx-0.0.8.dist-info/METADATA
trphysx-0.0.8.dist-info/WHEEL
trphysx-0.0.8.dist-info/top_level.txt
trphysx-0.0.8.dist-info/RECORD
