Metadata-Version: 2.1
Name: trphysx
Version: 0.0.8
Summary: Transformers for modeling physical systems
Home-page: https://github.com/zabaras/transformer-physx
Author: Nicholas Geneva
Author-email: ngeneva@nd.edu
License: MIT
Project-URL: Bug Reports, https://github.com/zabaras/transformer-physx/issues
Project-URL: Source, https://github.com/zabaras/transformer-physx
Keywords: transformers,physics,surrogate,machine learning,deep learning
Platform: UNKNOWN
Classifier: Development Status :: 2 - Pre-Alpha
Classifier: Intended Audience :: Science/Research
Classifier: Topic :: Scientific/Engineering :: Artificial Intelligence
Classifier: License :: OSI Approved :: MIT License
Classifier: Programming Language :: Python :: 3
Classifier: Programming Language :: Python :: 3.6
Classifier: Programming Language :: Python :: 3.7
Classifier: Programming Language :: Python :: 3.8
Classifier: Programming Language :: Python :: 3.9
Requires-Python: >=3.6, <4
Requires-Dist: torch (>=1.7.0)
Requires-Dist: filelock (>=3.0.0)
Requires-Dist: h5py (>=2.9.0)
Requires-Dist: numpy (>=1.15.0)
Requires-Dist: matplotlib (>=3.0.0)
